django_ckeditors/__init__.py
django_ckeditors/admin.py
django_ckeditors/apps.py
django_ckeditors/exceptions.py
django_ckeditors/fields.py
django_ckeditors/forms.py
django_ckeditors/helpers.py
django_ckeditors/image.py
django_ckeditors/models.py
django_ckeditors/urls.py
django_ckeditors/views.py
django_ckeditors/widgets.py
django_ckeditors/templates/django_ckeditors/widget.html
django_ckeditors-2025.5.22.3.dist-info/licenses/LICENSE
django_ckeditors-2025.5.22.3.dist-info/METADATA
django_ckeditors-2025.5.22.3.dist-info/WHEEL
django_ckeditors-2025.5.22.3.dist-info/top_level.txt
django_ckeditors-2025.5.22.3.dist-info/RECORD
