Metadata-Version: 2.4
Name: django-ckeditors
Version: 2025.5.22.3
Summary: CKEditors for Django.
Author-email: Vladislav Khoboko <vladislah@gmail.com>, Mark Sevelj <mark.sevelj@dunwright.com.au>
License: BSD-3-Clause
Project-URL: homepage, https://pypi.org/project/django-ckeditors/
Project-URL: repository, https://github.com/imAsparky/django-ckeditors.git
Keywords: CKEditor,CKEditors,Django
Classifier: Development Status :: 2 - Pre-Alpha
Classifier: Environment :: Web Environment
Classifier: Framework :: Django
Classifier: Framework :: Django :: 2.2
Classifier: Framework :: Django :: 3.0
Classifier: Framework :: Django :: 4.0
Classifier: Framework :: Django :: 5.0
Classifier: Intended Audience :: Developers
Classifier: License :: OSI Approved :: BSD License
Classifier: Operating System :: OS Independent
Classifier: Programming Language :: Python
Classifier: Programming Language :: Python :: 3.7
Classifier: Programming Language :: Python :: 3.8
Classifier: Programming Language :: Python :: 3.9
Classifier: Programming Language :: Python :: 3.10
Classifier: Programming Language :: Python :: 3.11
Classifier: Programming Language :: Python :: 3.12
Classifier: Programming Language :: Python :: 3.13
Classifier: Topic :: Internet :: WWW/HTTP
Classifier: Topic :: Internet :: WWW/HTTP :: Dynamic Content
Requires-Python: >=3.7
License-File: LICENSE
Requires-Dist: Django>=2.2
Requires-Dist: Pillow
Requires-Dist: filetype
Provides-Extra: dev
Requires-Dist: bandit[toml]==1.7.6; extra == "dev"
Requires-Dist: black==22.12.0; extra == "dev"
Requires-Dist: codespell==2.2.2; extra == "dev"
Requires-Dist: coverage==7.4.0; extra == "dev"
Requires-Dist: mypy==1.8.0; extra == "dev"
Requires-Dist: mypy-extensions==1.0.0; extra == "dev"
Requires-Dist: pytest==7.4.4; extra == "dev"
Requires-Dist: pytest-cov==4.0.0; extra == "dev"
Requires-Dist: pytest-django==4.5.2; extra == "dev"
Requires-Dist: pytest-mock==3.10.0; extra == "dev"
Requires-Dist: ruff; extra == "dev"
Requires-Dist: safety==2.3.5; extra == "dev"
Requires-Dist: types-setuptools==65.6.0.2; extra == "dev"
Requires-Dist: typing_extensions==4.9.0; extra == "dev"
Dynamic: license-file
